tests/__init__.py
tests/test_auth.py
tests/test_treeschema.py
tests/catalog/__init__.py
tests/catalog/test_base_serializer.py
tests/catalog/test_data_field.py
tests/catalog/test_data_schema.py
tests/catalog/test_data_store.py
tests/catalog/test_field_value.py
tests/catalog/test_lineage.py
tests/catalog/test_transformation.py
tests/catalog/test_transformation_link.py
tests/catalog/test_user.py
tests/integrations/__init__.py
tests/integrations/test_dbt.py
treeschema/__init__.py
treeschema/auth.py
treeschema/exceptions.py
treeschema/treeschema.py
treeschema/ts_enums.py
treeschema/api/__init__.py
treeschema/api/client.py
treeschema/api/endpoints.py
treeschema/catalog/__init__.py
treeschema/catalog/base_serializer.py
treeschema/catalog/data_field.py
treeschema/catalog/data_schema.py
treeschema/catalog/data_store.py
treeschema/catalog/field_value.py
treeschema/catalog/lineage.py
treeschema/catalog/tags.py
treeschema/catalog/transformation.py
treeschema/catalog/transformation_link.py
treeschema/catalog/user.py
treeschema/integrations/__init__.py
treeschema/integrations/dbt.py
treeschema-1.0.8.dist-info/LICENSE
treeschema-1.0.8.dist-info/METADATA
treeschema-1.0.8.dist-info/WHEEL
treeschema-1.0.8.dist-info/top_level.txt
treeschema-1.0.8.dist-info/RECORD
