Metadata-Version: 2.1
Name: treeschema
Version: 1.0.8
Summary: A python client that simplifies interactions with the Tree Schema REST API.
Home-page: https://github.com/tree-schema/tree-schema-python
Author: Tree Schema
Author-email: info@treeschema.com
License: UNKNOWN
Project-URL: Bug Reports, https://github.com/tree-schema/tree-schema-python/issues
Project-URL: Source, https://github.com/tree-schema/tree-schema-python
Project-URL: Documentation, https://developer.treeschema.com/python-client
Keywords: data lineage,metadata
Platform: UNKNOWN
Classifier: Programming Language :: Python :: 3
Classifier: License :: OSI Approved :: MIT License
Classifier: Operating System :: OS Independent
Requires-Dist: requests (>=2.22.0)
Provides-Extra: test
Requires-Dist: mock ; extra == 'test'
Requires-Dist: pytest ; extra == 'test'
Requires-Dist: Sphinx (==3.2.1) ; extra == 'test'
Requires-Dist: sphinx-rtd-theme (==0.5.0) ; extra == 'test'
